SynapseTrie/__init__.py
SynapseTrie/trie.py
SynapseTrie/utilities.py
tests/__init__.py
tests/test_trie.py
SynapseTrie-0.3.dist-info/LICENSE
SynapseTrie-0.3.dist-info/METADATA
SynapseTrie-0.3.dist-info/WHEEL
SynapseTrie-0.3.dist-info/top_level.txt
SynapseTrie-0.3.dist-info/RECORD
